pizzapi/__init__.py
pizzapi/address.py
pizzapi/coupon.py
pizzapi/customer.py
pizzapi/menu.py
pizzapi/order.py
pizzapi/payment.py
pizzapi/store.py
pizzapi/track.py
pizzapi/urls.py
pizzapi/utils.py
pizzapi-0.0.4.dist-info/DESCRIPTION.rst
pizzapi-0.0.4.dist-info/METADATA
pizzapi-0.0.4.dist-info/RECORD
pizzapi-0.0.4.dist-info/WHEEL
pizzapi-0.0.4.dist-info/metadata.json
pizzapi-0.0.4.dist-info/top_level.txt
tests/__init__.py
tests/test_address.py
tests/test_menu.py
