Metadata-Version: 2.0
Name: pizzapi
Version: 0.0.4
Summary: A Python wrapper for the Dominos Pizza API
Home-page: https://github.com/aluttik/pizzapi
Author: aluttik
Author-email: aluttik@gmail.com
License: MIT
Keywords: dominos pizza api
Platform: UNKNOWN
Classifier: Development Status :: 3 - Alpha
Classifier: License :: OSI Approved :: MIT License
Classifier: Programming Language :: Python
Classifier: Programming Language :: Python :: 2.7
Classifier: Programming Language :: Python :: 3.6
Classifier: Programming Language :: Python :: Implementation :: CPython
Classifier: Programming Language :: Python :: Implementation :: PyPy
Requires-Dist: pyhamcrest
Requires-Dist: requests
Requires-Dist: xmltodict
